[
    {
        "runId":  "R01",
        "kind":  "dev",
        "runDir":  "c:\\moschops_01\\docs\\09-training-runs\\runs\\2026-05-27_21-16-ts001-10run-lab\\R01-dev",
        "horizon":  5,
        "folds":  5,
        "embargo":  5,
        "grid":  "0.45,0.50,0.55,0.60",
        "selectedThreshold":  0.6,
        "selectionMode":  "fallback-risk-first",
        "constraintsSatisfied":  false,
        "trades":  0,
        "netReturnPct":  0,
        "profitFactor":  0,
        "maxDrawdownPct":  0,
        "stressNetReturnPct":  0,
        "stressProfitFactor":  0,
        "score":  -20
    },
    {
        "runId":  "R02",
        "kind":  "dev",
        "runDir":  "c:\\moschops_01\\docs\\09-training-runs\\runs\\2026-05-27_21-16-ts001-10run-lab\\R02-dev",
        "horizon":  5,
        "folds":  6,
        "embargo":  5,
        "grid":  "0.40,0.45,0.50,0.55",
        "selectedThreshold":  0.55,
        "selectionMode":  "fallback-risk-first",
        "constraintsSatisfied":  false,
        "trades":  47,
        "netReturnPct":  0.3984,
        "profitFactor":  1.0271,
        "maxDrawdownPct":  -9.943,
        "stressNetReturnPct":  -1.2466,
        "stressProfitFactor":  0.9204,
        "score":  -14.4404
    },
    {
        "runId":  "R03",
        "kind":  "dev",
        "runDir":  "c:\\moschops_01\\docs\\09-training-runs\\runs\\2026-05-27_21-16-ts001-10run-lab\\R03-dev",
        "horizon":  5,
        "folds":  5,
        "embargo":  10,
        "grid":  "0.45,0.50,0.55,0.60",
        "selectedThreshold":  0.6,
        "selectionMode":  "fallback-risk-first",
        "constraintsSatisfied":  false,
        "trades":  0,
        "netReturnPct":  0,
        "profitFactor":  0,
        "maxDrawdownPct":  0,
        "stressNetReturnPct":  0,
        "stressProfitFactor":  0,
        "score":  -20
    },
    {
        "runId":  "R04",
        "kind":  "dev",
        "runDir":  "c:\\moschops_01\\docs\\09-training-runs\\runs\\2026-05-27_21-16-ts001-10run-lab\\R04-dev",
        "horizon":  3,
        "folds":  5,
        "embargo":  5,
        "grid":  "0.45,0.50,0.55,0.60",
        "selectedThreshold":  0.6,
        "selectionMode":  "fallback-risk-first",
        "constraintsSatisfied":  false,
        "trades":  0,
        "netReturnPct":  0,
        "profitFactor":  0,
        "maxDrawdownPct":  0,
        "stressNetReturnPct":  0,
        "stressProfitFactor":  0,
        "score":  -20
    },
    {
        "runId":  "R05",
        "kind":  "dev",
        "runDir":  "c:\\moschops_01\\docs\\09-training-runs\\runs\\2026-05-27_21-16-ts001-10run-lab\\R05-dev",
        "horizon":  7,
        "folds":  5,
        "embargo":  5,
        "grid":  "0.40,0.45,0.50,0.55",
        "selectedThreshold":  0.55,
        "selectionMode":  "fallback-risk-first",
        "constraintsSatisfied":  false,
        "trades":  72,
        "netReturnPct":  -5.2114,
        "profitFactor":  0.8236,
        "maxDrawdownPct":  -15.0426,
        "stressNetReturnPct":  -7.7314,
        "stressProfitFactor":  0.7524,
        "score":  -30.008
    },
    {
        "runId":  "R06",
        "kind":  "dev",
        "runDir":  "c:\\moschops_01\\docs\\09-training-runs\\runs\\2026-05-27_21-16-ts001-10run-lab\\R06-dev",
        "horizon":  10,
        "folds":  5,
        "embargo":  5,
        "grid":  "0.40,0.45,0.50,0.55",
        "selectedThreshold":  0.55,
        "selectionMode":  "fallback-risk-first",
        "constraintsSatisfied":  false,
        "trades":  99,
        "netReturnPct":  -14.3854,
        "profitFactor":  0.7642,
        "maxDrawdownPct":  -32.1081,
        "stressNetReturnPct":  -17.8504,
        "stressProfitFactor":  0.717,
        "score":  -58.5814
    },
    {
        "runId":  "R07",
        "kind":  "dev",
        "runDir":  "c:\\moschops_01\\docs\\09-training-runs\\runs\\2026-05-27_21-16-ts001-10run-lab\\R07-dev",
        "horizon":  5,
        "folds":  7,
        "embargo":  10,
        "grid":  "0.50,0.55,0.60,0.65",
        "selectedThreshold":  0.65,
        "selectionMode":  "fallback-risk-first",
        "constraintsSatisfied":  false,
        "trades":  0,
        "netReturnPct":  0,
        "profitFactor":  0,
        "maxDrawdownPct":  0,
        "stressNetReturnPct":  0,
        "stressProfitFactor":  0,
        "score":  -20
    },
    {
        "runId":  "R08",
        "kind":  "dev",
        "runDir":  "c:\\moschops_01\\docs\\09-training-runs\\runs\\2026-05-27_21-16-ts001-10run-lab\\R08-dev",
        "horizon":  7,
        "folds":  6,
        "embargo":  10,
        "grid":  "0.45,0.50,0.55,0.60",
        "selectedThreshold":  0.6,
        "selectionMode":  "fallback-risk-first",
        "constraintsSatisfied":  false,
        "trades":  3,
        "netReturnPct":  -0.62,
        "profitFactor":  0.4565,
        "maxDrawdownPct":  -0.7076,
        "stressNetReturnPct":  -0.725,
        "stressProfitFactor":  0.4012,
        "score":  -15.4895
    },
    {
        "runId":  "R09",
        "kind":  "dev",
        "runDir":  "c:\\moschops_01\\docs\\09-training-runs\\runs\\2026-05-27_21-16-ts001-10run-lab\\R09-dev",
        "horizon":  3,
        "folds":  6,
        "embargo":  10,
        "grid":  "0.50,0.55,0.60,0.65",
        "selectedThreshold":  0.55,
        "selectionMode":  "constrained",
        "constraintsSatisfied":  true,
        "trades":  47,
        "netReturnPct":  -1.325,
        "profitFactor":  0.9083,
        "maxDrawdownPct":  -6.8684,
        "stressNetReturnPct":  -2.97,
        "stressProfitFactor":  0.807,
        "score":  -16.1963
    },
    {
        "runId":  "R10",
        "kind":  "holdout",
        "runDir":  "c:\\moschops_01\\docs\\09-training-runs\\runs\\2026-05-27_21-16-ts001-10run-lab\\R10-holdout-final",
        "horizon":  5,
        "folds":  6,
        "embargo":  5,
        "grid":  "0.40,0.45,0.50,0.55",
        "selectedThreshold":  0.55,
        "selectionMode":  "fallback-risk-first",
        "constraintsSatisfied":  false,
        "trades":  3,
        "netReturnPct":  3.8012,
        "profitFactor":  999,
        "maxDrawdownPct":  0,
        "stressNetReturnPct":  3.6962,
        "stressProfitFactor":  999,
        "score":  7995.8012
    }
]
